{
  "desert": {
    "$id": "desert Encounters",
    "Table": [
      {
        "Floor": "1",
        "Ceiling": "1",
        "Result": "A cairn of different sized skulls has been heaped up"
      },
      {
        "Floor": "2",
        "Ceiling": "2",
        "Result": "A cloud on the horizon rapidly approaches and appears to be a swarm of large insects as it approaches"
      },
      {
        "Floor": "3",
        "Ceiling": "3",
        "Result": "A cloudburst briefly drenches the desert and small flowers rapidly grow up through the sand"
      },
      {
        "Floor": "4",
        "Ceiling": "4",
        "Result": "A crooked and skeletal tower made from metal struts rises out of the desert"
      },
      {
        "Floor": "5",
        "Ceiling": "5",
        "Result": "A depression marks what used to be a lake once, now surrounded by dead vegetation"
      },
      {
        "Floor": "6",
        "Ceiling": "6",
        "Result": "A dune appears to have an unusually regular shape"
      },
      {
        "Floor": "7",
        "Ceiling": "7",
        "Result": "A goat grazing on some nearby shrubs suddenly vanishes, as something erupts from the ground and grabs it before disappearing again"
      },
      {
        "Floor": "8",
        "Ceiling": "8",
        "Result": "A huge crater, several miles across, blocks the way"
      },
      {
        "Floor": "9",
        "Ceiling": "9",
        "Result": "A huge plume of dust is on the horizon"
      },
      {
        "Floor": "10",
        "Ceiling": "10",
        "Result": "A large, spider-like shape can be seen in the distance, moving with a jerky, mechanical looking motion"
      },
      {
        "Floor": "11",
        "Ceiling": "11",
        "Result": "A large, winding depression in the desert marks the remains of a now dried-up river"
      },
      {
        "Floor": "12",
        "Ceiling": "12",
        "Result": "A pit with collapsing sides has been dug into the desert"
      },
      {
        "Floor": "13",
        "Ceiling": "13",
        "Result": "A settlement made from bits and pieces of salvaged pre-apocalypse materials has been destroyed by something large passing through it"
      },
      {
        "Floor": "14",
        "Ceiling": "14",
        "Result": "A single, mostly intact skyscraper rises out of the desert"
      },
      {
        "Floor": "15",
        "Ceiling": "15",
        "Result": "A small dust devil spins into view and keeps pace, seeming to be behaving intelligently and adjusting course as you do"
      },
      {
        "Floor": "16",
        "Ceiling": "16",
        "Result": "A small oasis contains a pool of clear water, but this is surrounded by dead plants and animals"
      },
      {
        "Floor": "17",
        "Ceiling": "17",
        "Result": "A tentacle lashes out of the sand and snatches a bird out of the air above it, dragging it below the surface"
      },
      {
        "Floor": "18",
        "Ceiling": "18",
        "Result": "A vortex of wind, like a dust devil but much larger, rises out of the desert"
      },
      {
        "Floor": "19",
        "Ceiling": "19",
        "Result": "A village, still largely intact, is almost completely buried by the sand, forming a small hillock that is noticeable from some distance"
      },
      {
        "Floor": "20",
        "Ceiling": "20",
        "Result": "A wadi wends across the desert, clearly once a river bed but it doesn't appear to have contained water in some time"
      },
      {
        "Floor": "21",
        "Ceiling": "21",
        "Result": "An expanse of cracked tarmac, now mostly covered in sand"
      },
      {
        "Floor": "22",
        "Ceiling": "22",
        "Result": "An oasis looks to be the only source of water for some distance"
      },
      {
        "Floor": "23",
        "Ceiling": "23",
        "Result": "An oddly-regular dune proves to have covered the subtly arched metal roof of a large building"
      },
      {
        "Floor": "24",
        "Ceiling": "24",
        "Result": "Bits and pieces of wood and metal stick out of the sand, the remains of a caravan that, if excavated, appears to have been recently swallowed up by the sand"
      },
      {
        "Floor": "25",
        "Ceiling": "25",
        "Result": "Bolts of what looks like lightning strike down in sequence, though the sky is without cloud and the lightning appears to be striking the same spot"
      },
      {
        "Floor": "26",
        "Ceiling": "26",
        "Result": "Bricks and concrete blocks have been arranged into what appears to be a crude temple"
      },
      {
        "Floor": "27",
        "Ceiling": "27",
        "Result": "Broken eggshells litter the sand"
      },
      {
        "Floor": "28",
        "Ceiling": "28",
        "Result": "Broken glass jars have been heaped into a pile"
      },
      {
        "Floor": "29",
        "Ceiling": "29",
        "Result": "Buried in the sand are a number of old war machines, all badly damaged and partially melted"
      },
      {
        "Floor": "30",
        "Ceiling": "30",
        "Result": "By the bank of a concrete channel stands a worn concrete building"
      },
      {
        "Floor": "31",
        "Ceiling": "31",
        "Result": "Charred, partially melted lines have been cut in the sand in regular rows, where the desert has been subjected to intense, focused heat"
      },
      {
        "Floor": "32",
        "Ceiling": "32",
        "Result": "Concrete rises out of the ground, the remains, judging by bollards and posts on it, of a dock, though there is no water around"
      },
      {
        "Floor": "33",
        "Ceiling": "33",
        "Result": "Cracked concrete surrounds a circular opening in the desert"
      },
      {
        "Floor": "34",
        "Ceiling": "34",
        "Result": "Damaged vehicles have been pulled into a ring and bits and pieces of metal used to fortify the gaps"
      },
      {
        "Floor": "35",
        "Ceiling": "35",
        "Result": "Detritus and sand has drifted against the sides of a convoy of abandoned military vehicles"
      },
      {
        "Floor": "36",
        "Ceiling": "36",
        "Result": "Flames are rising out of the desert from what looks like a pool of liquid"
      },
      {
        "Floor": "37",
        "Ceiling": "37",
        "Result": "Fragments of flesh and bone can be found in a wide area, coming from several different creatures"
      },
      {
        "Floor": "38",
        "Ceiling": "38",
        "Result": "Fulgurites can be found in the sand, where lightning has struck, only the fulgurites are enormous, several feet across, far larger than could be done by lightning"
      },
      {
        "Floor": "39",
        "Ceiling": "39",
        "Result": "Glints of light can be seen from some distance away, pieces of metal sticking out of the desert that are reflecting the sun"
      },
      {
        "Floor": "40",
        "Ceiling": "40",
        "Result": "Grazing on some desert shrubs is a camel when suddenly a nearby dune lurches forwards and completely covers the animal"
      },
      {
        "Floor": "41",
        "Ceiling": "41",
        "Result": "Humps and grooves in the desert mark the remains of a lost village"
      },
      {
        "Floor": "42",
        "Ceiling": "42",
        "Result": "In the near distance, the sand is moving in a straight line as something is clearly moving beneath the surface"
      },
      {
        "Floor": "43",
        "Ceiling": "43",
        "Result": "Just under the surface of the sand are a host of mummified corpses, once buried deeper but now partially exposed where the sand has blown away"
      },
      {
        "Floor": "44",
        "Ceiling": "44",
        "Result": "Leaning out of the sand is an old sign that has been worn away by sandstorms so that it can no longer be read"
      },
      {
        "Floor": "45",
        "Ceiling": "45",
        "Result": "Light flickers from the top of a sand dune"
      },
      {
        "Floor": "46",
        "Ceiling": "46",
        "Result": "Meat-eating wormlike creatures live in the sand here and will attack any living creature that spends too much time on one spot"
      },
      {
        "Floor": "47",
        "Ceiling": "47",
        "Result": "Melted and now rusty metal sticks out of the sand, surrounded by destroyed buildings and slumped metal storage tanks"
      },
      {
        "Floor": "48",
        "Ceiling": "48",
        "Result": "Meteorites fall from the sky and hit the desert with a rumble in the near distance"
      },
      {
        "Floor": "49",
        "Ceiling": "49",
        "Result": "Nestled in the desert is a lush valley full of flora and fauna"
      },
      {
        "Floor": "50",
        "Ceiling": "50",
        "Result": "Nomads wearing bits and pieces of old protective clothing are leading some camels across the desert"
      },
      {
        "Floor": "51",
        "Ceiling": "51",
        "Result": "Now mostly buried by drifting sand is a complex of buildings that once was a hotel"
      },
      {
        "Floor": "52",
        "Ceiling": "52",
        "Result": "Occasionally, the sand moves as something burrows beneath it"
      },
      {
        "Floor": "53",
        "Ceiling": "53",
        "Result": "On the horizon can be seen a large shape that is moving steadily away from you"
      },
      {
        "Floor": "54",
        "Ceiling": "54",
        "Result": "One of the sand dunes in the near distance appears to be moving slowly but steadily"
      },
      {
        "Floor": "55",
        "Ceiling": "55",
        "Result": "Part of the desert is blocked off behind a curving stone wall with a broken centre, the ruined remains of a dam"
      },
      {
        "Floor": "56",
        "Ceiling": "56",
        "Result": "Pieces of metal tube are partially buried in the desert, with other bits and pieces of broken metal scattered around"
      },
      {
        "Floor": "57",
        "Ceiling": "57",
        "Result": "Plants surround an oasis which offers the only water for some distance"
      },
      {
        "Floor": "58",
        "Ceiling": "58",
        "Result": "Pools of black liquid rest on the surface"
      },
      {
        "Floor": "59",
        "Ceiling": "59",
        "Result": "Ragged tents and damaged tent poles are partially buried in the sand"
      },
      {
        "Floor": "60",
        "Ceiling": "60",
        "Result": "Rain briefly falls from the sky as clouds rapidly appear then dissipate"
      },
      {
        "Floor": "61",
        "Ceiling": "61",
        "Result": "Regularly spaced stone structures, roughly rectangular in cross section but with rounded ends, rise out of the desert"
      },
      {
        "Floor": "62",
        "Ceiling": "62",
        "Result": "Resting on its side is an old, and now badly damaged, tanker vessel"
      },
      {
        "Floor": "63",
        "Ceiling": "63",
        "Result": "Rising out of the sand is a black stone pillar bearing strange carvings"
      },
      {
        "Floor": "64",
        "Ceiling": "64",
        "Result": "Running across the desert, and sometimes disappearing below its surface, is a large metal pipe, several feet in diameter"
      },
      {
        "Floor": "65",
        "Ceiling": "65",
        "Result": "Running across the desert are two parallel lines of metal"
      },
      {
        "Floor": "66",
        "Ceiling": "66",
        "Result": "Sand is rising in the air and hanging motionless for several minutes before falling back down"
      },
      {
        "Floor": "67",
        "Ceiling": "67",
        "Result": "Scarabs are lying on the ground"
      },
      {
        "Floor": "68",
        "Ceiling": "68",
        "Result": "Scavenger birds circle in the air in the distance, settling down to the ground"
      },
      {
        "Floor": "69",
        "Ceiling": "69",
        "Result": "Scraggly shrubs are growing in the desert"
      },
      {
        "Floor": "70",
        "Ceiling": "70",
        "Result": "Shaped stones stick out of the sand"
      },
      {
        "Floor": "71",
        "Ceiling": "71",
        "Result": "Shipping crates are partially buried in the sand"
      },
      {
        "Floor": "72",
        "Ceiling": "72",
        "Result": "Shrubs with blood-red veins running through their branches grow in a patch"
      },
      {
        "Floor": "73",
        "Ceiling": "73",
        "Result": "Skeletons of many animals, most looking to be domestic herd animals, are partially covered by a sand dune"
      },
      {
        "Floor": "74",
        "Ceiling": "74",
        "Result": "Small holes riddle the surrounding desert and occasionally a glimpse of movement can be seen as something that looks like a tentacle lashes out from them"
      },
      {
        "Floor": "75",
        "Ceiling": "75",
        "Result": "Small scorpions suddenly erupt out of the sand as they detect movement"
      },
      {
        "Floor": "76",
        "Ceiling": "76",
        "Result": "Small sparks of light mark where pieces of metal are in the sand"
      },
      {
        "Floor": "77",
        "Ceiling": "77",
        "Result": "Sticking out of the sand are what appear to be the ribs of an immense beast"
      },
      {
        "Floor": "78",
        "Ceiling": "78",
        "Result": "Stretching across the desert are the remains of a road"
      },
      {
        "Floor": "79",
        "Ceiling": "79",
        "Result": "Stubs of destroyed skyscrapers rise out of the sand, bearing the marks of intense heat and explosions"
      },
      {
        "Floor": "80",
        "Ceiling": "80",
        "Result": "The desert here is extremely dry and anyone venturing into it feels the moisture being sucked right out of them"
      },
      {
        "Floor": "81",
        "Ceiling": "81",
        "Result": "The desert's sand has been turned into glass by intense heat for many miles"
      },
      {
        "Floor": "82",
        "Ceiling": "82",
        "Result": "The end of a large metal cylinder sticks out of the sand"
      },
      {
        "Floor": "83",
        "Ceiling": "83",
        "Result": "The end of a shipping container pokes out of a sand dune, the doors open"
      },
      {
        "Floor": "84",
        "Ceiling": "84",
        "Result": "The head of a stone statue sticks out of the sand"
      },
      {
        "Floor": "85",
        "Ceiling": "85",
        "Result": "The mummified corpse of a long dead traveller partially sticks out of the sand"
      },
      {
        "Floor": "86",
        "Ceiling": "86",
        "Result": "The remains of a limestone outcropping sticks out of the desert"
      },
      {
        "Floor": "87",
        "Ceiling": "87",
        "Result": "The sand has collapsed into a hole, at the bottom of which is a tunnel on which there are metal tracks"
      },
      {
        "Floor": "88",
        "Ceiling": "88",
        "Result": "The sand is in constant movement, continually forming shapes of various things, including anything living that draws near"
      },
      {
        "Floor": "89",
        "Ceiling": "89",
        "Result": "The sand is moving and a large lizard that is scuttling across it is suddenly swallowed up"
      },
      {
        "Floor": "90",
        "Ceiling": "90",
        "Result": "The sand starts to slide and open out into a hole"
      },
      {
        "Floor": "91",
        "Ceiling": "91",
        "Result": "The temperature of this part of the desert is extremely high, even during the night, and moving through it is difficult and dangerous"
      },
      {
        "Floor": "92",
        "Ceiling": "92",
        "Result": "There is a dark cloud on the horizon that doesn't seem to move"
      },
      {
        "Floor": "93",
        "Ceiling": "93",
        "Result": "Tied to a dead-looking shrub is the skeleton of a long-dead camel"
      },
      {
        "Floor": "94",
        "Ceiling": "94",
        "Result": "Tracks have been left in the sand by something very large with claws"
      },
      {
        "Floor": "95",
        "Ceiling": "95",
        "Result": "Travelling at speed across the desert is a raised berm of sand, seemingly caused by something moving rapidly just below the surface"
      },
      {
        "Floor": "96",
        "Ceiling": "96",
        "Result": "Two parallel lines of dead trees are partially buried in the sand"
      },
      {
        "Floor": "97",
        "Ceiling": "97",
        "Result": "Water flows from a stack of rocks before soaking away into the ground"
      },
      {
        "Floor": "98",
        "Ceiling": "98",
        "Result": "What look like camels are travelling in the near distance, though they all appear to be oddly shaped"
      },
      {
        "Floor": "99",
        "Ceiling": "99",
        "Result": "What were once ancient monuments have now been shattered, scattering sandstone blocks across the landscape"
      },
      {
        "Floor": "100",
        "Ceiling": "100",
        "Result": "Wire fences surround a large area of land, though the fences are damaged, broken and, in some places, melted"
      }
    ]
  },
  "forest": {
    "$id": "forest Encounters",
    "Table": [
      {
        "Floor": "1",
        "Ceiling": "1",
        "Result": "A bird hobbles along the path, with an apparently broken wing"
      },
      {
        "Floor": "2",
        "Ceiling": "2",
        "Result": "A bird swoops down to grab a mouse from the forest floor, but is grabbed by a tentacle that unwraps from the mouse's back and dragged down, where the mouse rips it apart"
      },
      {
        "Floor": "3",
        "Ceiling": "3",
        "Result": "A branch falls from a tree and it looks as if the tree it fell from was deliberately trying to hit someone with the branch"
      },
      {
        "Floor": "4",
        "Ceiling": "4",
        "Result": "A buzzing noise can be heard from some distance away"
      },
      {
        "Floor": "5",
        "Ceiling": "5",
        "Result": "A clearing in the woods is unusually regularly shaped, flat and level and the grass is thin and sickly is places"
      },
      {
        "Floor": "6",
        "Ceiling": "6",
        "Result": "A copse of trees that look as if they are apple trees bearing fruit"
      },
      {
        "Floor": "7",
        "Ceiling": "7",
        "Result": "A crack cuts through the ground, several feet wide"
      },
      {
        "Floor": "8",
        "Ceiling": "8",
        "Result": "A crash can be heard as a tree suddenly falls"
      },
      {
        "Floor": "9",
        "Ceiling": "9",
        "Result": "A hedgehog walks across the path, its spines clearly metallic in nature"
      },
      {
        "Floor": "10",
        "Ceiling": "10",
        "Result": "A hill rises up out of the forest, one that seems strangely regular in shape"
      },
      {
        "Floor": "11",
        "Ceiling": "11",
        "Result": "A huge pit has been dug into the forest floor, and it looks to be almost completely filled with bones"
      },
      {
        "Floor": "12",
        "Ceiling": "12",
        "Result": "A huge spiderweb stretches between two trees, sparkling when it catches the light"
      },
      {
        "Floor": "13",
        "Ceiling": "13",
        "Result": "A large beetle, several inches long, walks slowly across the trail"
      },
      {
        "Floor": "14",
        "Ceiling": "14",
        "Result": "A large ground vehicle has been swallowed up by the forest"
      },
      {
        "Floor": "15",
        "Ceiling": "15",
        "Result": "A log is covered in huge fungi"
      },
      {
        "Floor": "16",
        "Ceiling": "16",
        "Result": "A low-lying concrete structure has yet to be colonised by any of the forest plants"
      },
      {
        "Floor": "17",
        "Ceiling": "17",
        "Result": "A nauseatingly strong stench can suddenly be smelled, making it difficult to breathe"
      },
      {
        "Floor": "18",
        "Ceiling": "18",
        "Result": "A pile of dung from something large sits on the trail"
      },
      {
        "Floor": "19",
        "Ceiling": "19",
        "Result": "A pit will open in the ground when creatures walk on top of it"
      },
      {
        "Floor": "20",
        "Ceiling": "20",
        "Result": "A pool of seemingly clean and clear water is surrounded by dead vegetation and several animal skeletons"
      },
      {
        "Floor": "21",
        "Ceiling": "21",
        "Result": "A skeleton is wrapped in poison oak"
      },
      {
        "Floor": "22",
        "Ceiling": "22",
        "Result": "A snake ripples across the path in a strangely mechanical manner"
      },
      {
        "Floor": "23",
        "Ceiling": "23",
        "Result": "A squirrel runs up the trunk of a tree and into an opening, followed by crunching sounds and blood drips out of the hole"
      },
      {
        "Floor": "24",
        "Ceiling": "24",
        "Result": "A stream wends its way through the forest"
      },
      {
        "Floor": "25",
        "Ceiling": "25",
        "Result": "A tree creaks as the vines that are wrapped around it visibly tighten"
      },
      {
        "Floor": "26",
        "Ceiling": "26",
        "Result": "A tree root curls across the trail"
      },
      {
        "Floor": "27",
        "Ceiling": "27",
        "Result": "A tree suddenly flickers out of existence, before appearing once more, then becomes transparent"
      },
      {
        "Floor": "28",
        "Ceiling": "28",
        "Result": "All the trees here look dead, lacking leaves and with brittle branches, yet they somehow also seem to be alive"
      },
      {
        "Floor": "29",
        "Ceiling": "29",
        "Result": "Amongst the rest of the trees, some growing in two parallel lines can be made out with a clearer patch between them"
      },
      {
        "Floor": "30",
        "Ceiling": "30",
        "Result": "An animal runs across the trail ahead"
      },
      {
        "Floor": "31",
        "Ceiling": "31",
        "Result": "An apparent tree stump lashes out with tentacles if approached too closely, attempting to drag creatures into a gaping maw that opens up in its side"
      },
      {
        "Floor": "32",
        "Ceiling": "32",
        "Result": "An old campfire sits in a small clearing, surrounded by a ring of stones"
      },
      {
        "Floor": "33",
        "Ceiling": "33",
        "Result": "Birds perch on the nearby branches"
      },
      {
        "Floor": "34",
        "Ceiling": "34",
        "Result": "Bits and pieces of old, once-manufactured debris, have been arranged into an arrow"
      },
      {
        "Floor": "35",
        "Ceiling": "35",
        "Result": "Blue-glowing moss adheres to the trunks of nearby trees"
      },
      {
        "Floor": "36",
        "Ceiling": "36",
        "Result": "Brambles bear vile-looking green fruit"
      },
      {
        "Floor": "37",
        "Ceiling": "37",
        "Result": "Branches have been arranged in what used to be a hide, though it has been partially destroyed"
      },
      {
        "Floor": "38",
        "Ceiling": "38",
        "Result": "Bright flowers grow on the forest floor in a patch of sunlight"
      },
      {
        "Floor": "39",
        "Ceiling": "39",
        "Result": "Bulbous growths are growing on the trunks of some of the trees, seemingly siphoning life out of the trees to which they are attached"
      },
      {
        "Floor": "40",
        "Ceiling": "40",
        "Result": "Clouds of midges hang beneath the trees"
      },
      {
        "Floor": "41",
        "Ceiling": "41",
        "Result": "Croaking noises can be traced back to a pond where a number of brightly, and differently, coloured frogs can be found"
      },
      {
        "Floor": "42",
        "Ceiling": "42",
        "Result": "Crossing the trail ahead is a column of what initially appear to be ants, but which have exoskeletons that look metallic"
      },
      {
        "Floor": "43",
        "Ceiling": "43",
        "Result": "Dead animals and birds have been strung up from the trees"
      },
      {
        "Floor": "44",
        "Ceiling": "44",
        "Result": "Dead leaves lie on the forest floor, rapidly decomposing and rotting away as they are watched"
      },
      {
        "Floor": "45",
        "Ceiling": "45",
        "Result": "Denser patches of trees border lighter ones, with the lighter patches seeming to form several paths, each dozens of yards wide and linked to each other"
      },
      {
        "Floor": "46",
        "Ceiling": "46",
        "Result": "Every plant in this area, from trees to shrubs to vines, is growing tightly together, even growing into each other in places"
      },
      {
        "Floor": "47",
        "Ceiling": "47",
        "Result": "Fruit trees are growing in this part of the forest, in what looks like it might once have been an orchard"
      },
      {
        "Floor": "48",
        "Ceiling": "48",
        "Result": "Holes have been cut into the ground"
      },
      {
        "Floor": "49",
        "Ceiling": "49",
        "Result": "Huge bitemarks have been taken out of several trees in the area, in some cases cutting halfway through the trunks"
      },
      {
        "Floor": "50",
        "Ceiling": "50",
        "Result": "In a bank of soil is a large hole, several feet in diameter"
      },
      {
        "Floor": "51",
        "Ceiling": "51",
        "Result": "Ivy grows up rectangular constructions that are now mostly hidden by the overgrowth"
      },
      {
        "Floor": "52",
        "Ceiling": "52",
        "Result": "Ivy has wrapped itself around all the nearby trees"
      },
      {
        "Floor": "53",
        "Ceiling": "53",
        "Result": "Large, clawed tracks cross the path, showing where several large creatures have recently passed"
      },
      {
        "Floor": "54",
        "Ceiling": "54",
        "Result": "Large, shattered tubes of metal that were once joined together are now smothered by the trees"
      },
      {
        "Floor": "55",
        "Ceiling": "55",
        "Result": "Looming over a rotting corpse is a plant about 8' tall"
      },
      {
        "Floor": "56",
        "Ceiling": "56",
        "Result": "Lumps rise out of the forest, all strangely regular in shape and spaced apart from each other"
      },
      {
        "Floor": "57",
        "Ceiling": "57",
        "Result": "Lying on the ground is the remains of a very large nest, surrounded by broken fragments of equally large shells"
      },
      {
        "Floor": "58",
        "Ceiling": "58",
        "Result": "Metal spikes have been driven into the trunk of a tree"
      },
      {
        "Floor": "59",
        "Ceiling": "59",
        "Result": "Moss is draped around the trunks of dead and dying trees"
      },
      {
        "Floor": "60",
        "Ceiling": "60",
        "Result": "Nearby trees creak as their position visibly changes without any wind, the branches reaching out for any creature nearby"
      },
      {
        "Floor": "61",
        "Ceiling": "61",
        "Result": "Nearly transparent butterflies dance in a beam of sunlight"
      },
      {
        "Floor": "62",
        "Ceiling": "62",
        "Result": "Nettles guard the path on both sides, their leaves blocking part of it"
      },
      {
        "Floor": "63",
        "Ceiling": "63",
        "Result": "Nuts patter down from the trees above"
      },
      {
        "Floor": "64",
        "Ceiling": "64",
        "Result": "Old stonework surrounds a partially buried entrance to what looks to be a tunnel complex beneath the forest"
      },
      {
        "Floor": "65",
        "Ceiling": "65",
        "Result": "Part of the forest has been burnt, with old ash and stumps littering the ground"
      },
      {
        "Floor": "66",
        "Ceiling": "66",
        "Result": "Poking through the surface is a small piece of metal, the trigger mechanism of an old, but still functional, mine"
      },
      {
        "Floor": "67",
        "Ceiling": "67",
        "Result": "Popping noises are heard as seed pods on a nearby plant explode"
      },
      {
        "Floor": "68",
        "Ceiling": "68",
        "Result": "Puddles of liquid dot the ground"
      },
      {
        "Floor": "69",
        "Ceiling": "69",
        "Result": "Pulsing green puffballs explode with force if they are touched or disturbed in any way"
      },
      {
        "Floor": "70",
        "Ceiling": "70",
        "Result": "Rain falls on the forest from above"
      },
      {
        "Floor": "71",
        "Ceiling": "71",
        "Result": "Several odd-shaped lumps in the vegetation prove to hide what look like small constructions for playing on"
      },
      {
        "Floor": "72",
        "Ceiling": "72",
        "Result": "Shrubs here have thorns that are both very long, at least 3” in length, and very sharp, easily ripping light clothing and penetrating skin"
      },
      {
        "Floor": "73",
        "Ceiling": "73",
        "Result": "Standing next to the path is what looks like a sign bearing a map of the area, though it is heavily worn and the few pieces that can be made out do not appear to be accurate"
      },
      {
        "Floor": "74",
        "Ceiling": "74",
        "Result": "Sticky green sap is oozing from the trunk of a tree"
      },
      {
        "Floor": "75",
        "Ceiling": "75",
        "Result": "Stone foundations rise out of the ground, marking where many buildings used to stand"
      },
      {
        "Floor": "76",
        "Ceiling": "76",
        "Result": "Symbols have been carved into the trunks of a number of trees"
      },
      {
        "Floor": "77",
        "Ceiling": "77",
        "Result": "The deafening roar of something huge is heard briefly in the distance"
      },
      {
        "Floor": "78",
        "Ceiling": "78",
        "Result": "The forest here is strangely quiet"
      },
      {
        "Floor": "79",
        "Ceiling": "79",
        "Result": "The forest surrounds a lake here, and in a less-overgrown clearing are the remains of a number of buildings"
      },
      {
        "Floor": "80",
        "Ceiling": "80",
        "Result": "The ground suddenly gives way, revealing a concrete room below ground whose ceiling has just collapsed, potentially dumping creatures into it"
      },
      {
        "Floor": "81",
        "Ceiling": "81",
        "Result": "The plants have pulsing veins running through them, nearly blood red in colour"
      },
      {
        "Floor": "82",
        "Ceiling": "82",
        "Result": "The soil of the forest's floor has turned into oozing black muck"
      },
      {
        "Floor": "83",
        "Ceiling": "83",
        "Result": "The trees are horribly disfigured, with strange, pustulent growths and weeping sores, yet they are still growing"
      },
      {
        "Floor": "84",
        "Ceiling": "84",
        "Result": "The trees look strangely metallic in composition"
      },
      {
        "Floor": "85",
        "Ceiling": "85",
        "Result": "The trees here move almost imperceptibly when they are not being watched, blocking off paths and subtly diverting travellers"
      },
      {
        "Floor": "86",
        "Ceiling": "86",
        "Result": "The upper branches of the trees here have grown tightly together, blocking light from reaching the forest floor"
      },
      {
        "Floor": "87",
        "Ceiling": "87",
        "Result": "The vegetation of the forest in this area is clearly dead and nothing is growing to replace it"
      },
      {
        "Floor": "88",
        "Ceiling": "88",
        "Result": "The way is partially blocked by a large patch of mud"
      },
      {
        "Floor": "89",
        "Ceiling": "89",
        "Result": "The woods are broken up by a circular clearing, in which nothing lives"
      },
      {
        "Floor": "90",
        "Ceiling": "90",
        "Result": "Thick slime covers the fallen leaves on the ground"
      },
      {
        "Floor": "91",
        "Ceiling": "91",
        "Result": "Thorny brambles lash out with flexible limbs at anything passing, seeking to drive the thorns into flesh"
      },
      {
        "Floor": "92",
        "Ceiling": "92",
        "Result": "Trees and other vegetation have been reduced to pulp by the passage of something very large and heavy"
      },
      {
        "Floor": "93",
        "Ceiling": "93",
        "Result": "Trees and plants cover a huge pile of mangled metal, where many different broken pieces have been stacked up"
      },
      {
        "Floor": "94",
        "Ceiling": "94",
        "Result": "Trees have been ripped out of the ground by their roots and arranged in what can only be described as a huge nest"
      },
      {
        "Floor": "95",
        "Ceiling": "95",
        "Result": "Trees in a small grove are either dead or dying"
      },
      {
        "Floor": "96",
        "Ceiling": "96",
        "Result": "Vegetation has grown over the still mostly intact remains of what looks like an armoured vehicle of some kind"
      },
      {
        "Floor": "97",
        "Ceiling": "97",
        "Result": "Vines are growing in a strangely regular manner, in what appears to be straight lines"
      },
      {
        "Floor": "98",
        "Ceiling": "98",
        "Result": "Vines have wrapped around an old sign, suggesting that this part of the forest wasn't always forest"
      },
      {
        "Floor": "99",
        "Ceiling": "99",
        "Result": "Vines twitch when living creatures approach and will lash out to entangle them when the creatures get close enough"
      },
      {
        "Floor": "100",
        "Ceiling": "100",
        "Result": "When stepped on, a patch of ground gives off a metallic sound"
      }
    ]
  },
  "mountain": {
    "$id": "mountain Encounters",
    "Table": [
      {
        "Floor": "1",
        "Ceiling": "1",
        "Result": "A beam of light, visible even during the day, stabs out from the top of one of the peaks"
      },
      {
        "Floor": "2",
        "Ceiling": "2",
        "Result": "A castle stands on a small rise"
      },
      {
        "Floor": "3",
        "Ceiling": "3",
        "Result": "A cliff has been deeply cut by a melted slice that runs from its top to its base"
      },
      {
        "Floor": "4",
        "Ceiling": "4",
        "Result": "A crevasse running up the mountain is blocked by thick, metallic-looking webbing"
      },
      {
        "Floor": "5",
        "Ceiling": "5",
        "Result": "A dam that used to block a valley has been destroyed"
      },
      {
        "Floor": "6",
        "Ceiling": "6",
        "Result": "A damaged construction looks to be a path for coming quickly down the side of the mountain, but it tilts up at the bottom"
      },
      {
        "Floor": "7",
        "Ceiling": "7",
        "Result": "A deep, circular pit is partly blocked by two halves of a circular door that have either partially opened or partially closed"
      },
      {
        "Floor": "8",
        "Ceiling": "8",
        "Result": "A metal mast rises from a peak, sliced cleanly through partway up"
      },
      {
        "Floor": "9",
        "Ceiling": "9",
        "Result": "A mountain has been split in two, a tremendous crack dividing the two halves"
      },
      {
        "Floor": "10",
        "Ceiling": "10",
        "Result": "A neighbouring mountain's top ends in a shattered stump, where something has clearly destroyed it"
      },
      {
        "Floor": "11",
        "Ceiling": "11",
        "Result": "A pile of metal has been stacked by the side of a former road"
      },
      {
        "Floor": "12",
        "Ceiling": "12",
        "Result": "A rickety wooden tower with a square room at the top sits on a low rise overlooking a wooded valley"
      },
      {
        "Floor": "13",
        "Ceiling": "13",
        "Result": "A rockslide has fallen onto, and mostly destroyed, what looks to have once been a mountain village"
      },
      {
        "Floor": "14",
        "Ceiling": "14",
        "Result": "A series of cliffs are cut into the mountain here, with smooth, sheer sides that bear the signs of once being partially molten"
      },
      {
        "Floor": "15",
        "Ceiling": "15",
        "Result": "A series of metal pylons are joined together in places by metal cables"
      },
      {
        "Floor": "16",
        "Ceiling": "16",
        "Result": "A small plateau partway up the mountain has several badly damaged military vehicles on it"
      },
      {
        "Floor": "17",
        "Ceiling": "17",
        "Result": "A small valley nestled in the mountains is mostly filled with a lake filled with steaming black water"
      },
      {
        "Floor": "18",
        "Ceiling": "18",
        "Result": "A small, wooden hut, now decaying with age, sits at the top of a damaged path"
      },
      {
        "Floor": "19",
        "Ceiling": "19",
        "Result": "A stream running down the mountain bears signs that it was once running in an artificial bed, but has since worn away at the sides"
      },
      {
        "Floor": "20",
        "Ceiling": "20",
        "Result": "A trestle bridge with metal rails on top runs across a valley"
      },
      {
        "Floor": "21",
        "Ceiling": "21",
        "Result": "A tunnel has been cut into the mountain and a road leads into it"
      },
      {
        "Floor": "22",
        "Ceiling": "22",
        "Result": "A valley has been almost completely filled with rubble that has been shattered from the mountain it is in"
      },
      {
        "Floor": "23",
        "Ceiling": "23",
        "Result": "A valley high up the mountain is gradually being filled with a glacier that is crushing the damaged village that used to sit in the valley"
      },
      {
        "Floor": "24",
        "Ceiling": "24",
        "Result": "A worn metal sign on a bent metal pole stands at the edge of the cliff"
      },
      {
        "Floor": "25",
        "Ceiling": "25",
        "Result": "An old machine is still gradually chipping away at the mountainside"
      },
      {
        "Floor": "26",
        "Ceiling": "26",
        "Result": "Animals dot the mountainside"
      },
      {
        "Floor": "27",
        "Ceiling": "27",
        "Result": "At night, a light can be seen flashing at the top of another peak"
      },
      {
        "Floor": "28",
        "Ceiling": "28",
        "Result": "At the bottom of a cliff can be seen a large pile of yellowish-white items"
      },
      {
        "Floor": "29",
        "Ceiling": "29",
        "Result": "Blasted pieces of metal, former, and now broken, thick metal doors, partially block a tunnel carved into the mountain"
      },
      {
        "Floor": "30",
        "Ceiling": "30",
        "Result": "Boulders lie scattered around, all scorched and broken by heat and force"
      },
      {
        "Floor": "31",
        "Ceiling": "31",
        "Result": "Broken bits of glass and metal cover a large expanse of the mountains, one that appears to be in sunlight for most of the day"
      },
      {
        "Floor": "32",
        "Ceiling": "32",
        "Result": "Cut into the mountainside is the entrance to a very old mine"
      },
      {
        "Floor": "33",
        "Ceiling": "33",
        "Result": "Crossing a gorge is a damaged bridge made from metal and stone"
      },
      {
        "Floor": "34",
        "Ceiling": "34",
        "Result": "Crossing a large crevasse is a worn-looking metal pipe a couple of feet across"
      },
      {
        "Floor": "35",
        "Ceiling": "35",
        "Result": "Damaged wooden poles, each several feet high, stand at the edges of a decaying road cut into the mountainside"
      },
      {
        "Floor": "36",
        "Ceiling": "36",
        "Result": "Dozens of rectangular stone cairns dot a small plateau"
      },
      {
        "Floor": "37",
        "Ceiling": "37",
        "Result": "Driven partway into the mountain is some sort of cylindrical device that appears to have impacted at great speed and from above"
      },
      {
        "Floor": "38",
        "Ceiling": "38",
        "Result": "During the night, a blue glow can be seen coming from various parts of the mountain"
      },
      {
        "Floor": "39",
        "Ceiling": "39",
        "Result": "Fastened to a cliff face is a metal ladder"
      },
      {
        "Floor": "40",
        "Ceiling": "40",
        "Result": "Half a building sits on the edge of a cliff"
      },
      {
        "Floor": "41",
        "Ceiling": "41",
        "Result": "Huge claw marks have been scored into the side of a cliff"
      },
      {
        "Floor": "42",
        "Ceiling": "42",
        "Result": "Huge, inhuman faces have been carved into the mountainside"
      },
      {
        "Floor": "43",
        "Ceiling": "43",
        "Result": "In a small box canyon off a mountain valley is a thick-walled stone building"
      },
      {
        "Floor": "44",
        "Ceiling": "44",
        "Result": "Inside a small cave cut into the mountain are a number of bodies, seemingly posed as if they died in the middle of activities, and became mummified after they died"
      },
      {
        "Floor": "45",
        "Ceiling": "45",
        "Result": "It looks like a cutting was made in the mountain here, perhaps for a road to travel through, but the sides of the cutting have been demolished, filling it with debris"
      },
      {
        "Floor": "46",
        "Ceiling": "46",
        "Result": "Lamps on the top of metal poles glow during the night"
      },
      {
        "Floor": "47",
        "Ceiling": "47",
        "Result": "Large metal poles dot the mountainside, each evenly spaced"
      },
      {
        "Floor": "48",
        "Ceiling": "48",
        "Result": "Nestled in a small valley, amidst a copse of trees, is a small, rundown, wooden hunting lodge"
      },
      {
        "Floor": "49",
        "Ceiling": "49",
        "Result": "On a distant slope are several, presumably very large, humanoid figures"
      },
      {
        "Floor": "50",
        "Ceiling": "50",
        "Result": "On an artificially flattened area are a number of broken items on mounts positioned by the edge where there is a damaged railing"
      },
      {
        "Floor": "51",
        "Ceiling": "51",
        "Result": "On the top of the mountain's peak is a large building with a niche in one side"
      },
      {
        "Floor": "52",
        "Ceiling": "52",
        "Result": "One of the mountains in the range has clearly been almost completely destroyed, with only a few fragments remaining"
      },
      {
        "Floor": "53",
        "Ceiling": "53",
        "Result": "Part of the mountain has been quarried away"
      },
      {
        "Floor": "54",
        "Ceiling": "54",
        "Result": "Partway up a cliff is a large, rectangular opening partially blocked by two metal doors"
      },
      {
        "Floor": "55",
        "Ceiling": "55",
        "Result": "Plastic tables with integral benches stand in overgrown patches of grass by the sides of crumbling and weed-ridden tarmac"
      },
      {
        "Floor": "56",
        "Ceiling": "56",
        "Result": "Plumes of flame burn constantly from several fissures in the mountainside"
      },
      {
        "Floor": "57",
        "Ceiling": "57",
        "Result": "Protruding from the mountainside is a large metal vent from which a cloud of steam is being emitted"
      },
      {
        "Floor": "58",
        "Ceiling": "58",
        "Result": "Rubble blocks the entrance to a cave"
      },
      {
        "Floor": "59",
        "Ceiling": "59",
        "Result": "Running through the centre of a mountain valley is a clear stream"
      },
      {
        "Floor": "60",
        "Ceiling": "60",
        "Result": "Scattered across a goodly amount of the mountain are fragments that look to have come from several different flying craft"
      },
      {
        "Floor": "61",
        "Ceiling": "61",
        "Result": "Several metal cylinders are scattered across part of the mountain, each a couple of feet long"
      },
      {
        "Floor": "62",
        "Ceiling": "62",
        "Result": "Scorch marks in the approximate shape of humans in cowering poses blacken a partially melted cliff"
      },
      {
        "Floor": "63",
        "Ceiling": "63",
        "Result": "Several pipes stick out of the side of the mountain, in different sizes"
      },
      {
        "Floor": "64",
        "Ceiling": "64",
        "Result": "Several ruined buildings are scattered across a flat spot on the mountainside, surrounded by other wreckage including a large, flat area of cracked concrete"
      },
      {
        "Floor": "65",
        "Ceiling": "65",
        "Result": "Slime covers every surface of a small valley in the mountain"
      },
      {
        "Floor": "66",
        "Ceiling": "66",
        "Result": "Soil and rock partially fill a valley"
      },
      {
        "Floor": "67",
        "Ceiling": "67",
        "Result": "Something that looks like smoke is pluming from a mountain peak, but it does not appear to be moving with the wind; rather, of its own accord"
      },
      {
        "Floor": "68",
        "Ceiling": "68",
        "Result": "Spanning partway across a mountain valley is an aqueduct, the centre section of which has been destroyed"
      },
      {
        "Floor": "69",
        "Ceiling": "69",
        "Result": "Spindly metal towers have been built on the mountain"
      },
      {
        "Floor": "70",
        "Ceiling": "70",
        "Result": "Spoil heaps stand next to a tunnel carved into the rock"
      },
      {
        "Floor": "71",
        "Ceiling": "71",
        "Result": "Standing on a flat space at near the top of the mountain is a collection of small buildings, with various instruments attached to their roofs"
      },
      {
        "Floor": "72",
        "Ceiling": "72",
        "Result": "Standing on a small rise with good views in every direction is a small, flattopped pyramid of concrete"
      },
      {
        "Floor": "73",
        "Ceiling": "73",
        "Result": "Steps have been cut into the mountainside, with broken stumps showing where metal railings used to be fixed"
      },
      {
        "Floor": "74",
        "Ceiling": "74",
        "Result": "Sticking out from both cliffs of a narrow gorge, a gorge that appears to have been caused by an earthquake or something, are the sheathings of the severed parts of a tunnel that is now exposed"
      },
      {
        "Floor": "75",
        "Ceiling": "75",
        "Result": "Sticking partway out of the side of the mountain is a huge machine with a drill at one end"
      },
      {
        "Floor": "76",
        "Ceiling": "76",
        "Result": "Stretching part of the way across a chasm is a damaged bridge"
      },
      {
        "Floor": "77",
        "Ceiling": "77",
        "Result": "The land continually shakes with earthquakes of varying degrees of severity and plumes of smoke and ash rise from most of the peaks in the range"
      },
      {
        "Floor": "78",
        "Ceiling": "78",
        "Result": "The mountain forms a plateau here"
      },
      {
        "Floor": "79",
        "Ceiling": "79",
        "Result": "The mountain has been badly damaged, with an enormous crater eating away much of one side"
      },
      {
        "Floor": "80",
        "Ceiling": "80",
        "Result": "The mountain's rock is gradually moving as it is watched, slowly changing shape"
      },
      {
        "Floor": "81",
        "Ceiling": "81",
        "Result": "The mountain's rock is slumped and scarred where it has been exposed to intense heat"
      },
      {
        "Floor": "82",
        "Ceiling": "82",
        "Result": "The mountainside is vibrating from a deep, regular noise coming from deep inside it"
      },
      {
        "Floor": "83",
        "Ceiling": "83",
        "Result": "The mountainside is suddenly hit by a cloudburst"
      },
      {
        "Floor": "84",
        "Ceiling": "84",
        "Result": "The path is blocked by a steep-sided gorge with smooth sides that appears to have been melted into the rock"
      },
      {
        "Floor": "85",
        "Ceiling": "85",
        "Result": "The remains of what look to have been a farm can be found amongst the remains of fields of grass"
      },
      {
        "Floor": "86",
        "Ceiling": "86",
        "Result": "The rock of the mountain is damaged and crumbling where a waterfall has sprayed"
      },
      {
        "Floor": "87",
        "Ceiling": "87",
        "Result": "The side of a cliff, if touched, turns out not to be real but some sort of projection"
      },
      {
        "Floor": "88",
        "Ceiling": "88",
        "Result": "The sun briefly disappears as the shadow of something very large passes over, heading towards another peak"
      },
      {
        "Floor": "89",
        "Ceiling": "89",
        "Result": "The trail up the mountain looks like it was once maintained, with metal and stone reinforcements to the cliffside and path itself, as well as a handrail"
      },
      {
        "Floor": "90",
        "Ceiling": "90",
        "Result": "Thick, tall metal doors block what looks like an entrance into the mountain"
      },
      {
        "Floor": "91",
        "Ceiling": "91",
        "Result": "Three vehicles, each badly damaged and bearing a large, partially melted metal tube on their back, are positioned so that they overlook the lowlands"
      },
      {
        "Floor": "92",
        "Ceiling": "92",
        "Result": "Topping a nearby peak is a circular building with a shattered dome that used to be its roof"
      },
      {
        "Floor": "93",
        "Ceiling": "93",
        "Result": "Tracks made of metal run along the mountainside"
      },
      {
        "Floor": "94",
        "Ceiling": "94",
        "Result": "Trees are growing straight out of the mountain's rock"
      },
      {
        "Floor": "95",
        "Ceiling": "95",
        "Result": "Two niches have been carved into the side of a cliff"
      },
      {
        "Floor": "96",
        "Ceiling": "96",
        "Result": "Vertical shafts have been cut into the mountain, with pieces of shattered metal at their tops that once would have blocked them off"
      },
      {
        "Floor": "97",
        "Ceiling": "97",
        "Result": "Water is falling from a hole in a cliffside"
      },
      {
        "Floor": "98",
        "Ceiling": "98",
        "Result": "What looks as if it was once a flow of molten lava covers much of the mountain here, even though the mountain isn't volcanic in nature"
      },
      {
        "Floor": "99",
        "Ceiling": "99",
        "Result": "What looks like it was once a road has been damaged by a rockfall"
      },
      {
        "Floor": "100",
        "Ceiling": "100",
        "Result": "When a rock outcropping is more closely approached, it's clear that it once used to be some sort of bunker"
      }
    ]
  },
  "plains": {
    "$id": "plains Encounters",
    "Table": [
      {
        "Floor": "1",
        "Ceiling": "1",
        "Result": "A bird stoops out of the sky, swooping on something on the land below, but when it gets close to the ground it is dragged out of the sky and disappears"
      },
      {
        "Floor": "2",
        "Ceiling": "2",
        "Result": "A broken metal door is sent into the ground at a slant"
      },
      {
        "Floor": "3",
        "Ceiling": "3",
        "Result": "A circle of lights have been mounted on stakes"
      },
      {
        "Floor": "4",
        "Ceiling": "4",
        "Result": "A clanging noise can be heard in the distance"
      },
      {
        "Floor": "5",
        "Ceiling": "5",
        "Result": "A copse of trees is growing wild, but it looks like they were maintained at one point"
      },
      {
        "Floor": "6",
        "Ceiling": "6",
        "Result": "A dust devil is weaving its way across the plain, seemingly changing direction randomly"
      },
      {
        "Floor": "7",
        "Ceiling": "7",
        "Result": "A flat rock that looks to have been shaped crudely from a piece of concrete stands in the middle of the field"
      },
      {
        "Floor": "8",
        "Ceiling": "8",
        "Result": "A grey sludge is travelling across the ground in the near distance"
      },
      {
        "Floor": "9",
        "Ceiling": "9",
        "Result": "A huge pit has been cut into the ground here"
      },
      {
        "Floor": "10",
        "Ceiling": "10",
        "Result": "A jet of flame rises from a hole in the ground, easily visible from distance away during the day and even further at night"
      },
      {
        "Floor": "11",
        "Ceiling": "11",
        "Result": "A landing strip extends for hundreds of yards"
      },
      {
        "Floor": "12",
        "Ceiling": "12",
        "Result": "A large area of the plain is at least a dozen feet below the rest, seeming to mark a region where an underground structure or complex has collapsed"
      },
      {
        "Floor": "13",
        "Ceiling": "13",
        "Result": "A large crater contains a pool of foul-looking water in the bottom"
      },
      {
        "Floor": "14",
        "Ceiling": "14",
        "Result": "A large expanse of water is a lake, but a dead one judging by the smell"
      },
      {
        "Floor": "15",
        "Ceiling": "15",
        "Result": "A large pumping machine, now juddering and squealing with age and lack of maintenance, is still seemingly attempting to pump oil from the ground, judging by the debris near it"
      },
      {
        "Floor": "16",
        "Ceiling": "16",
        "Result": "A large trench has been cut in the ground here, going dozens of feet deep"
      },
      {
        "Floor": "17",
        "Ceiling": "17",
        "Result": "A length of oddly intact road, lined on each side by lampposts that come on at twilight, stretches through the plain for about a mile, before abruptly terminating"
      },
      {
        "Floor": "18",
        "Ceiling": "18",
        "Result": "A low hill is the highest point for some miles, providing a good view of the surrounding plains"
      },
      {
        "Floor": "19",
        "Ceiling": "19",
        "Result": "A low-lying building rises no more than a few feet above the surrounding plains"
      },
      {
        "Floor": "20",
        "Ceiling": "20",
        "Result": "A lump of rusty metal sticks up out of the ground"
      },
      {
        "Floor": "21",
        "Ceiling": "21",
        "Result": "A number of what were once large buildings rise up out of the plains here"
      },
      {
        "Floor": "22",
        "Ceiling": "22",
        "Result": "A pit has been partially dug into the plains"
      },
      {
        "Floor": "23",
        "Ceiling": "23",
        "Result": "A pool of water has a regular shape from a distance, and when approached it can be seen to be artificial"
      },
      {
        "Floor": "24",
        "Ceiling": "24",
        "Result": "A river cuts through the plains, the water hissing and bubbling as it does"
      },
      {
        "Floor": "25",
        "Ceiling": "25",
        "Result": "A river winding through the plains is notable for the concrete banks that keep it in its course, though the concrete is now crumbling and falling to pieces"
      },
      {
        "Floor": "26",
        "Ceiling": "26",
        "Result": "A scarecrow stands in a field of maintained crops, and several other fields can be seen, also with scarecrows"
      },
      {
        "Floor": "27",
        "Ceiling": "27",
        "Result": "A single rock lies in the middle of a field of grass"
      },
      {
        "Floor": "28",
        "Ceiling": "28",
        "Result": "A small spring bubbles out of the ground here, the water quickly soaking away into the ground"
      },
      {
        "Floor": "29",
        "Ceiling": "29",
        "Result": "A solitary tree looks as if it has been struck by lightning not once, but multiple times, yet it still seems to be alive"
      },
      {
        "Floor": "30",
        "Ceiling": "30",
        "Result": "A steep-sided crevasse several feet wide cuts through the plain here"
      },
      {
        "Floor": "31",
        "Ceiling": "31",
        "Result": "An array of metal structures has slumped under exposure to heat"
      },
      {
        "Floor": "32",
        "Ceiling": "32",
        "Result": "An extensive field of ash stretches for miles, everything, right down to the soil, having been burnt away"
      },
      {
        "Floor": "33",
        "Ceiling": "33",
        "Result": "An immense crater, several miles across, breaks the plain here"
      },
      {
        "Floor": "34",
        "Ceiling": "34",
        "Result": "Badly damaged fencing surrounds a number of what were once fields, and there are still crops growing wild, both in the fields and in the plains surrounding them, where seeds have travelled past the boundaries of the fences"
      },
      {
        "Floor": "35",
        "Ceiling": "35",
        "Result": "Bits and pieces of roads can be seen poking through the undergrowth, the surface clearly shattered and broken"
      },
      {
        "Floor": "36",
        "Ceiling": "36",
        "Result": "Broken cylinders of metal, some with seats inside, lie slumped and shattered across the ground"
      },
      {
        "Floor": "37",
        "Ceiling": "37",
        "Result": "Buildings, or the remains of them, for only a foot or so of the foundations remain, dot the plains here, the ruins of a small settlement"
      },
      {
        "Floor": "38",
        "Ceiling": "38",
        "Result": "Dead trees rise from the plains, each no more than a charcoal skeleton of what it used to be"
      },
      {
        "Floor": "39",
        "Ceiling": "39",
        "Result": "Dozens of vehicles have been dumped in a section of the plains, apparently towed there from somewhere else"
      },
      {
        "Floor": "40",
        "Ceiling": "40",
        "Result": "Dust covers the ground, swirling up every now and then in a breeze"
      },
      {
        "Floor": "41",
        "Ceiling": "41",
        "Result": "Embedded in the plain to some depth is a vast metal construction, from its appearance a flying fortress of some kind that has crashed"
      },
      {
        "Floor": "42",
        "Ceiling": "42",
        "Result": "Grassy mounds rise up from the plains, each with an oddly regular shape and positioning"
      },
      {
        "Floor": "43",
        "Ceiling": "43",
        "Result": "Here and there parts of buildings rise above the plains"
      },
      {
        "Floor": "44",
        "Ceiling": "44",
        "Result": "Human skulls have been mounted on stakes and used to demark a boundary on the plains"
      },
      {
        "Floor": "45",
        "Ceiling": "45",
        "Result": "In the distance, a vehicle flies several feet above the ground, leaving a trail of dust as it rapidly vanishes from sight"
      },
      {
        "Floor": "46",
        "Ceiling": "46",
        "Result": "In the distance, smoke covers a large expanse of the horizon, boiling up unto the sky in thick, black clouds"
      },
      {
        "Floor": "47",
        "Ceiling": "47",
        "Result": "Irrigation channels network the nearby plains"
      },
      {
        "Floor": "48",
        "Ceiling": "48",
        "Result": "Light glints from something on a rise in the distance"
      },
      {
        "Floor": "49",
        "Ceiling": "49",
        "Result": "Metal bones curve out of the ground here, seemingly from some enormous, skeletal robot"
      },
      {
        "Floor": "50",
        "Ceiling": "50",
        "Result": "Mounds of soil dot the plain, reminiscent of ant mounds, though much larger"
      },
      {
        "Floor": "51",
        "Ceiling": "51",
        "Result": "Mud is bubbling away in a pool, which proves to be boiling if touched"
      },
      {
        "Floor": "52",
        "Ceiling": "52",
        "Result": "Old wire fences stretch for miles, though they have been knocked down in many places"
      },
      {
        "Floor": "53",
        "Ceiling": "53",
        "Result": "Plants are growing from the plains, but they are all twisted and warped"
      },
      {
        "Floor": "54",
        "Ceiling": "54",
        "Result": "Poking up through the ground are the corners of what appear to be large metal boxes"
      },
      {
        "Floor": "55",
        "Ceiling": "55",
        "Result": "Protruding from the earth are a number of small metal cylinders, some with conical caps on top of them"
      },
      {
        "Floor": "56",
        "Ceiling": "56",
        "Result": "Regular openings dot the plains, large holes leading into deep silos in the ground"
      },
      {
        "Floor": "57",
        "Ceiling": "57",
        "Result": "Regularly-spaced dots, each metallic and a few inches across, have been driven into the ground"
      },
      {
        "Floor": "58",
        "Ceiling": "58",
        "Result": "Rising above the plain are the smooth sides of what looks to be a large fortress, though the sides are now marked by holes that have been blown through them and pieces have been scattered across the surroundings from explosions"
      },
      {
        "Floor": "59",
        "Ceiling": "59",
        "Result": "Rising out of the plains is a strangely regular lump, too small to be a true hill"
      },
      {
        "Floor": "60",
        "Ceiling": "60",
        "Result": "Rubble, presumably the remains of one or more buildings, is scattered across a wide area"
      },
      {
        "Floor": "61",
        "Ceiling": "61",
        "Result": "Scattered pieces of coloured fabric and lean-tos improvised from flat pieces of now crumbling metal and plastic mark what appears to be an old refugee camp"
      },
      {
        "Floor": "62",
        "Ceiling": "62",
        "Result": "Several ships, ranging from small to large, lie on their sides, partially covered by the dirt of the plains"
      },
      {
        "Floor": "63",
        "Ceiling": "63",
        "Result": "Shattered pillars of concrete rise above the plain, stretching for a few hundred yards before coming to an end"
      },
      {
        "Floor": "64",
        "Ceiling": "64",
        "Result": "Skeletons of what look like cows are standing in a nearby field"
      },
      {
        "Floor": "65",
        "Ceiling": "65",
        "Result": "Slumped lumps of metal in a line are the remains of various armoured vehicles that have been exposed to extreme heat"
      },
      {
        "Floor": "66",
        "Ceiling": "66",
        "Result": "Small holes dot the ground and every so often something like a prairie dog pokes its head up to take a look"
      },
      {
        "Floor": "67",
        "Ceiling": "67",
        "Result": "Smoke rises into the air some distance away"
      },
      {
        "Floor": "68",
        "Ceiling": "68",
        "Result": "Something streaks out of the sky and crashes into the ground with an explosion, sending rocks and dirt flying, in the near distance"
      },
      {
        "Floor": "69",
        "Ceiling": "69",
        "Result": "Standing in the plain is a single, clearly old, house, one that appears to be surprisingly intact and, moreover, not located near any other buildings"
      },
      {
        "Floor": "70",
        "Ceiling": "70",
        "Result": "Sticking out of the ground is a large, vaguely human looking, metal head"
      },
      {
        "Floor": "71",
        "Ceiling": "71",
        "Result": "Stone slabs poke through the ground here and there"
      },
      {
        "Floor": "72",
        "Ceiling": "72",
        "Result": "Strange barks can be heard coming closer, and a pack of doglike creatures, all of them deformed in some way, crests a rise"
      },
      {
        "Floor": "73",
        "Ceiling": "73",
        "Result": "Stretching partway across a river are the shattered remains of a bridge, a couple of vehicles still crumbling on it"
      },
      {
        "Floor": "74",
        "Ceiling": "74",
        "Result": "The corner of something a faded red in colour sticks out of the ground"
      },
      {
        "Floor": "75",
        "Ceiling": "75",
        "Result": "The dirt here has dried and started to blow away, revealing the mummified bodies of dozens of dead people that had been covered by it"
      },
      {
        "Floor": "76",
        "Ceiling": "76",
        "Result": "The grass here is thin and sickly-looking, as if it isn't getting enough nourishment"
      },
      {
        "Floor": "77",
        "Ceiling": "77",
        "Result": "The grass looks dry and dead, being brown and withered-looking, but on closer examination it proves to still be alive and growing"
      },
      {
        "Floor": "78",
        "Ceiling": "78",
        "Result": "The grass of the plains has been charred here by a massive burn scar"
      },
      {
        "Floor": "79",
        "Ceiling": "79",
        "Result": "The ground appears to be smooth dirt, free of vegetation, but if stepped on it proves to act like a liquid, even though it's made of solid matter, and anything attempting to move across it risks being sucked under"
      },
      {
        "Floor": "80",
        "Ceiling": "80",
        "Result": "The ground has been fused into a sheet of many different substances"
      },
      {
        "Floor": "81",
        "Ceiling": "81",
        "Result": "The ground has been sliced open in a rectangular cutting, several dozen feet deep and wide, and, allowing for the passage of time crumbling the walls slightly, perfectly regular in shape"
      },
      {
        "Floor": "82",
        "Ceiling": "82",
        "Result": "The ground is covered in a layer of fungus, with nothing else growing there"
      },
      {
        "Floor": "83",
        "Ceiling": "83",
        "Result": "The ground is thickly covered in craters, some overlapping each other but all looking to be about the same size"
      },
      {
        "Floor": "84",
        "Ceiling": "84",
        "Result": "The ground rings hollow and metallic when walked on, and cleaning away the dirt reveals a trapdoor made of metal"
      },
      {
        "Floor": "85",
        "Ceiling": "85",
        "Result": "The ground rumbles then a blast of liquid erupts from a hole in the ground"
      },
      {
        "Floor": "86",
        "Ceiling": "86",
        "Result": "The plain here is dead, as the soil has been turned into a thick layer of broken glass, thick enough that nothing has managed to break through the glass yet"
      },
      {
        "Floor": "87",
        "Ceiling": "87",
        "Result": "The plain is marred by a sinkhole here, whose steep sides slope down to a hole in what looks like a thick sheet of reinforced concrete"
      },
      {
        "Floor": "88",
        "Ceiling": "88",
        "Result": "The remains of shattered and destroyed buildings stretches into the distance for miles"
      },
      {
        "Floor": "89",
        "Ceiling": "89",
        "Result": "The soil and grass has been churned up by the passage of something with massive treads"
      },
      {
        "Floor": "90",
        "Ceiling": "90",
        "Result": "The sky darkens as a vast cloud of birds flies past above, covering the ground in mildly caustic droppings"
      },
      {
        "Floor": "91",
        "Ceiling": "91",
        "Result": "The way is blocked by an immense, steep-sided crack that cuts across the plain in a strangely regular line"
      },
      {
        "Floor": "92",
        "Ceiling": "92",
        "Result": "Thunder is heard in the distance and its origin is quickly seen, as a herd of beasts charges across the landscape"
      },
      {
        "Floor": "93",
        "Ceiling": "93",
        "Result": "Tree stumps and the shattered remains of trees stretch for some distance, suggesting that this area of the plains used to be wooded"
      },
      {
        "Floor": "94",
        "Ceiling": "94",
        "Result": "Twisted skeletal structures of metal stretch in a single line across the landscape"
      },
      {
        "Floor": "95",
        "Ceiling": "95",
        "Result": "Two parallel lines of melted and solidified metal stretch across the plains, bound to a mess of charred gravel and ash"
      },
      {
        "Floor": "96",
        "Ceiling": "96",
        "Result": "The stump of a building rises from the plains, debris scattered around it"
      },
      {
        "Floor": "97",
        "Ceiling": "97",
        "Result": "The wreck of an enormous war machine is partially buried in the ground, rents and tears in its metal armour showing where it was hit"
      },
      {
        "Floor": "98",
        "Ceiling": "98",
        "Result": "Wild crops are moving in a nearby field"
      },
      {
        "Floor": "99",
        "Ceiling": "99",
        "Result": "Winding through the plains is a dry river"
      },
      {
        "Floor": "100",
        "Ceiling": "100",
        "Result": "Yellowish-white things can be seen poking up through the grass"
      }
    ]
  },
  "swamp": {
    "$id": "swamp Encounters",
    "Table": [
      {
        "Floor": "1",
        "Ceiling": "1",
        "Result": "A bucket that used to contain water and fish has been overturned and lies in a large pool of blood that is still spreading out"
      },
      {
        "Floor": "2",
        "Ceiling": "2",
        "Result": "A channel has been ploughed through the swamp, one that is still raw and fresh, though it has filled with water"
      },
      {
        "Floor": "3",
        "Ceiling": "3",
        "Result": "A completely regular circular pool is filled with a thick black liquid, that clings to anything it touches and burns bare flesh"
      },
      {
        "Floor": "4",
        "Ceiling": "4",
        "Result": "A copse of trees in the swamp have a regular appearance to them, suggesting that they were once maintained, but have since grown wild"
      },
      {
        "Floor": "5",
        "Ceiling": "5",
        "Result": "A crooked steeple rises partly out of the swamp"
      },
      {
        "Floor": "6",
        "Ceiling": "6",
        "Result": "A flame burns on the surface of a pool, though it can be extinguished"
      },
      {
        "Floor": "7",
        "Ceiling": "7",
        "Result": "A hillock rising out of the swamp is the only dry land for some distance around, but every inch of it is covered in trees"
      },
      {
        "Floor": "8",
        "Ceiling": "8",
        "Result": "A huge metal ship has been broken apart and has sunk into the swamp"
      },
      {
        "Floor": "9",
        "Ceiling": "9",
        "Result": "A humming sound, reminiscent of insects but also sounding slightly mechanical in nature, comes from the distance"
      },
      {
        "Floor": "10",
        "Ceiling": "10",
        "Result": "A jumble of boats, all generally small in size, rises up from a pool of water and the surrounding shore"
      },
      {
        "Floor": "11",
        "Ceiling": "11",
        "Result": "A large expanse of water and mud covers the ground in front of the shattered remains of what used to be a dam"
      },
      {
        "Floor": "12",
        "Ceiling": "12",
        "Result": "A low bridge of pre-apocalyptic construction stretches across part of the swamp, though it is missing several sections"
      },
      {
        "Floor": "13",
        "Ceiling": "13",
        "Result": "A patch of mist hovers above a nearby pool"
      },
      {
        "Floor": "14",
        "Ceiling": "14",
        "Result": "A pool of pale green water is surrounded by various twisted looking plants, with strange water lilies growing in the water itself"
      },
      {
        "Floor": "15",
        "Ceiling": "15",
        "Result": "A pool of water in the swamp is steadily bubbling away and steam is rising from it"
      },
      {
        "Floor": "16",
        "Ceiling": "16",
        "Result": "A pool of water is filled with leeches which will latch onto anything that enters"
      },
      {
        "Floor": "17",
        "Ceiling": "17",
        "Result": "A pool of water that appears to be perfectly round in shape if investigated proves to be very deep and the top of an open concrete cylinder"
      },
      {
        "Floor": "18",
        "Ceiling": "18",
        "Result": "A slope covered in weeds, muck and algae rises gently up out of the swamp before terminating abruptly"
      },
      {
        "Floor": "19",
        "Ceiling": "19",
        "Result": "A thick rime of salt surrounds one of the marshy pools, and the water within the pool itself is extremely salty, far saltier than seawater, even though the rest of the swamp is freshwater"
      },
      {
        "Floor": "20",
        "Ceiling": "20",
        "Result": "A warped metal framework, with what looks like a ladder on the interior, leans at an angle out of the swamp"
      },
      {
        "Floor": "21",
        "Ceiling": "21",
        "Result": "A well-kept hut made from bits and pieces of salvaged pre-apocalyptic materials stands in one of the few comparatively dry areas"
      },
      {
        "Floor": "22",
        "Ceiling": "22",
        "Result": "A willow tree covered in blackened bark that is split in places"
      },
      {
        "Floor": "23",
        "Ceiling": "23",
        "Result": "An enormous Venus flytrap is growing out of the swamp"
      },
      {
        "Floor": "24",
        "Ceiling": "24",
        "Result": "Bits and pieces of assorted junk float on the top of a large, stagnant pool"
      },
      {
        "Floor": "25",
        "Ceiling": "25",
        "Result": "Bits and pieces of broken roadway lead to a tunnel mouth that heads into the ground"
      },
      {
        "Floor": "26",
        "Ceiling": "26",
        "Result": "Bits of a large snake are scattered across the path, where something has shredded it"
      },
      {
        "Floor": "27",
        "Ceiling": "27",
        "Result": "Branches of nearby plants are moving and the ripples cover the surface of a nearby pool, as if they are being acted on by the wind, but there is no wind"
      },
      {
        "Floor": "28",
        "Ceiling": "28",
        "Result": "Bright red berries grow on bushes in a marshy area"
      },
      {
        "Floor": "29",
        "Ceiling": "29",
        "Result": "Bubbles of foul-smelling and flammable gas rise up out of the swampy mire, popping with a nauseating stench"
      },
      {
        "Floor": "30",
        "Ceiling": "30",
        "Result": "Clouds of small biting insects fill the air above various ponds here"
      },
      {
        "Floor": "31",
        "Ceiling": "31",
        "Result": "Comparatively fresh human corpses lie on the ground, though they also appear to be slowly dissolving into it"
      },
      {
        "Floor": "32",
        "Ceiling": "32",
        "Result": "Creaking noises come from a nearby tree"
      },
      {
        "Floor": "33",
        "Ceiling": "33",
        "Result": "Cylindrical pieces of metal, as well as smaller fragments, fill a lot of a pool of water"
      },
      {
        "Floor": "34",
        "Ceiling": "34",
        "Result": "Draped in algae and moss is something that clearly looks artificial in nature"
      },
      {
        "Floor": "35",
        "Ceiling": "35",
        "Result": "Driven into the mud by some sort of immense weight are the flattened remains of several bodies, human by the looks of it"
      },
      {
        "Floor": "36",
        "Ceiling": "36",
        "Result": "During the day, the vegetation in this area appears twisted and deformed"
      },
      {
        "Floor": "37",
        "Ceiling": "37",
        "Result": "Fragments of broken stone cover the ground, pushed up in places where plants have grown and swallowed up by the muck in others"
      },
      {
        "Floor": "38",
        "Ceiling": "38",
        "Result": "Fungi grow profusely on every surface"
      },
      {
        "Floor": "39",
        "Ceiling": "39",
        "Result": "Hanging from the trees are small fetishes made from what look like human fingerbones as well as fragments of pre-apocalyptic items"
      },
      {
        "Floor": "40",
        "Ceiling": "40",
        "Result": "Herbs are growing in a swampy patch of ground"
      },
      {
        "Floor": "41",
        "Ceiling": "41",
        "Result": "Holes have been dug into the muck and, though most have filled up with water, metal can be glimpsed at the bottom of many of them"
      },
      {
        "Floor": "42",
        "Ceiling": "42",
        "Result": "Huge bones that appear to have a metallic cast to them curve up out of one of the pools of water"
      },
      {
        "Floor": "43",
        "Ceiling": "43",
        "Result": "In a stagnant pool of blackened and foul-melling water float several rusty meatal barrels"
      },
      {
        "Floor": "44",
        "Ceiling": "44",
        "Result": "In the near distance, a figure enshrouded in a hooded cloak quickly moves away, though with an uneven gait"
      },
      {
        "Floor": "45",
        "Ceiling": "45",
        "Result": "Lumps covered in algae and moss stick out of the mud and swampy water"
      },
      {
        "Floor": "46",
        "Ceiling": "46",
        "Result": "Metal wires are partially covered by moss, algae and the swamp itself"
      },
      {
        "Floor": "47",
        "Ceiling": "47",
        "Result": "Moss, algae and vines cover oddshaped lumps that rise out of the swamp"
      },
      {
        "Floor": "48",
        "Ceiling": "48",
        "Result": "Moss covers the ground here but, if it's watched for a period of time, the moss proves to be moving, gradually inching its way across the soil, leaving a steaming trail behind it"
      },
      {
        "Floor": "49",
        "Ceiling": "49",
        "Result": "Moss, of a bright, virulent green hue, covers the ground in a thick layer"
      },
      {
        "Floor": "50",
        "Ceiling": "50",
        "Result": "Much of the ground here has turned into thick black mud"
      },
      {
        "Floor": "51",
        "Ceiling": "51",
        "Result": "Oddments of structures poke up out of the swamp, covering a wide area"
      },
      {
        "Floor": "52",
        "Ceiling": "52",
        "Result": "Part of the swamp has collapsed here, into what looks like a metal and concrete structure"
      },
      {
        "Floor": "53",
        "Ceiling": "53",
        "Result": "Partially submerged in the swamp is a metal construction that looks like it once strode around on legs, but has collapsed into the mud"
      },
      {
        "Floor": "54",
        "Ceiling": "54",
        "Result": "Pieces of regularly-shaped metal protrude out of the swamp"
      },
      {
        "Floor": "55",
        "Ceiling": "55",
        "Result": "Pillars of metal jut up out of the swamp"
      },
      {
        "Floor": "56",
        "Ceiling": "56",
        "Result": "Protruding up out of the muck are the remains of enormous buildings"
      },
      {
        "Floor": "57",
        "Ceiling": "57",
        "Result": "Reeds growing out of the swampy waters are a bright red in colour"
      },
      {
        "Floor": "58",
        "Ceiling": "58",
        "Result": "Regularly-shaped mounds, though of different heights, rise out of a stretch of water, each covered in vines and algae"
      },
      {
        "Floor": "59",
        "Ceiling": "59",
        "Result": "Rising from the muck are a series of very large, thick walls, seemingly without joins"
      },
      {
        "Floor": "60",
        "Ceiling": "60",
        "Result": "Rising out of the swamp is a small hill of dry earth"
      },
      {
        "Floor": "61",
        "Ceiling": "61",
        "Result": "Rotting animal corpses surround a pool of crystal-clear water in the swamp"
      },
      {
        "Floor": "62",
        "Ceiling": "62",
        "Result": "Running through the swamp are the remains of an ancient road"
      },
      {
        "Floor": "63",
        "Ceiling": "63",
        "Result": "Rusting oddments of iron, along with still intact fragments of other alloys and perishing plastics, choke a small pool of water in the swamp"
      },
      {
        "Floor": "64",
        "Ceiling": "64",
        "Result": "Scattered across a wide area of the swamp are rocks and stones thickly covered in algae"
      },
      {
        "Floor": "65",
        "Ceiling": "65",
        "Result": "Several channels wending through the swamp are filled with faster-flowing water and look curiously regular in shape"
      },
      {
        "Floor": "66",
        "Ceiling": "66",
        "Result": "Several pieces of metal stick out from the surface of the swamp"
      },
      {
        "Floor": "67",
        "Ceiling": "67",
        "Result": "Sinking into the swamp are the shattered remains of houses, clustered like a village"
      },
      {
        "Floor": "68",
        "Ceiling": "68",
        "Result": "Skeletons fill a pool of swampy water, and more are scattered on the muddy banks"
      },
      {
        "Floor": "69",
        "Ceiling": "69",
        "Result": "Snakes fill one of the pools of water in the swamp in absurdly large numbers, twisting and slithering against each other"
      },
      {
        "Floor": "70",
        "Ceiling": "70",
        "Result": "Some sort of huge drilling has breached the swamp's surface and is now covered in a thick layer of earth and moss"
      },
      {
        "Floor": "71",
        "Ceiling": "71",
        "Result": "Standing at the top of a small hillock in the swamp is a very old stone building that looks as if it might pre-date the apocalypse by some time"
      },
      {
        "Floor": "72",
        "Ceiling": "72",
        "Result": "Steam is rising from a patch of swamp"
      },
      {
        "Floor": "73",
        "Ceiling": "73",
        "Result": "Sticking out of the swamp is what initially looks like an eyestalk, with an eye on the end, but which glints in a metallic manner"
      },
      {
        "Floor": "74",
        "Ceiling": "74",
        "Result": "Sticking up from a large, semi-solid pool of water are some curiously regular structures"
      },
      {
        "Floor": "75",
        "Ceiling": "75",
        "Result": "Sticking up out of the swamp is the wreck of a ship"
      },
      {
        "Floor": "76",
        "Ceiling": "76",
        "Result": "Stones surround what looks like a swamp-filled graveyard"
      },
      {
        "Floor": "77",
        "Ceiling": "77",
        "Result": "Sun glints off glass that is covered in vegetation"
      },
      {
        "Floor": "78",
        "Ceiling": "78",
        "Result": "Surrounding a low hillock of drier ground are the remains of a metal fence, once that has been crushed into the ground in places"
      },
      {
        "Floor": "79",
        "Ceiling": "79",
        "Result": "Tall concrete pillars rise up out of the swamp, stretching for some distance, suggesting that they supported something that was much larger than a bridge"
      },
      {
        "Floor": "80",
        "Ceiling": "80",
        "Result": "The marshy areas here have what look to be regular sides, though these are now hidden beneath growth and muck"
      },
      {
        "Floor": "81",
        "Ceiling": "81",
        "Result": "The remains of walls only a couple of feet high jut out of the swamp"
      },
      {
        "Floor": "82",
        "Ceiling": "82",
        "Result": "The ruins of buildings stick up out of the swamp, most not much more than stumps and smaller ones completely obscured by vines, algae and moss"
      },
      {
        "Floor": "83",
        "Ceiling": "83",
        "Result": "The stagnant water here forms a large pool that appears artificially shaped"
      },
      {
        "Floor": "84",
        "Ceiling": "84",
        "Result": "The surface of a nearby pool of water raises up as something large in the water briefly raises itself almost to the surface before submerging again"
      },
      {
        "Floor": "85",
        "Ceiling": "85",
        "Result": "The swamp here has become dry and dusty"
      },
      {
        "Floor": "86",
        "Ceiling": "86",
        "Result": "The water and mud in this area of the swamp has bits and pieces of bones from what look like thousands of bodies"
      },
      {
        "Floor": "87",
        "Ceiling": "87",
        "Result": "Tied up to the bank is a small, flat-bottomed boat suitable for traversing the swamp"
      },
      {
        "Floor": "88",
        "Ceiling": "88",
        "Result": "Trees here are rapidly dying and collapsing into the swamp"
      },
      {
        "Floor": "89",
        "Ceiling": "89",
        "Result": "Triangular mounds of earth, each at least 10' high and covered in vegetation, cross the swamp"
      },
      {
        "Floor": "90",
        "Ceiling": "90",
        "Result": "Trickling down a small hillock into the stagnant water is a small stream of fresh water"
      },
      {
        "Floor": "91",
        "Ceiling": "91",
        "Result": "Twisted and warped plants grow up through vile-looking water and putrid mud"
      },
      {
        "Floor": "92",
        "Ceiling": "92",
        "Result": "Twisted and mutated trees are growing around the edge of a pool full of black water"
      },
      {
        "Floor": "93",
        "Ceiling": "93",
        "Result": "Underneath the mud there seems to be a grid of metal"
      },
      {
        "Floor": "94",
        "Ceiling": "94",
        "Result": "Underneath the swamp's water and mud here is what feels like a solid surface beneath it"
      },
      {
        "Floor": "95",
        "Ceiling": "95",
        "Result": "Vegetation has been crushed in a wide path which is now covered in a layer of slime"
      },
      {
        "Floor": "96",
        "Ceiling": "96",
        "Result": "Water blasts up from a pool in the swamp, reaching at least a couple of dozen feet in height before ceasing"
      },
      {
        "Floor": "97",
        "Ceiling": "97",
        "Result": "What appear to be wooden cabins sinking into the muck are arranged along the shoreline of a large pool"
      },
      {
        "Floor": "98",
        "Ceiling": "98",
        "Result": "What look like stepping stones cross part of the swamp here"
      },
      {
        "Floor": "99",
        "Ceiling": "99",
        "Result": "What looks to be a sinkhole in the swamp, into which water and mud are slowly flowing, proves to lead to a tunnel whose roof has collapsed"
      },
      {
        "Floor": "100",
        "Ceiling": "100",
        "Result": "Wooden stakes rise out of the swamp, each topped with a skull"
      }
    ]
  }
}